{
  "appId": "com.glytch.chat",
  "productName": "Glytch Chat",
  "directories": {
    "output": "release"
  },
  "files": [
    "dist/**/*",
    "electron/main.js",
    "electron/preload.js",
    "package.json"
  ],
  "extraMetadata": {
    "main": "electron/main.js"
  },
  "afterPack": "electron/after-pack.cjs",
  "artifactName": "glytch-chat-${version}-${os}-${arch}.${ext}",
  "asar": true,
  "mac": {
    "target": [
      {
        "target": "dmg",
        "arch": [
          "x64",
          "arm64"
        ]
      }
    ],
    "category": "public.app-category.social-networking",
    "identity": null,
    "hardenedRuntime": false,
    "gatekeeperAssess": false
  },
  "dmg": {
    "sign": false
  },
  "win": {
    "target": [
      {
        "target": "nsis",
        "arch": [
          "x64"
        ]
      }
    ]
  },
  "nsis": {
    "oneClick": false,
    "allowToChangeInstallationDirectory": true
  },
  "publish": null
}
